Workbook
Name Aporte: Planilha1!$D$18
Name DividendoMensal: Planilha1!$D$25
Name PatrimonioAcumulado: Planilha1!$D$22
Name PrecoMedioCompra: Planilha1!#REF!
Name PrecoVenda: Planilha1!#REF!
Name QntdAnos: Planilha1!$D$19
Name QntdFIIsComprado: Planilha1!$D$16
Name QntdFIIsVend: Planilha1!#REF!
Name RendimentoCarteira: Planilha1!$D$13
Name Salario: Planilha1!$D$12
Name SugestaoInvestimento: Planilha1!$D$14
Name TaxaRendMensal: Planilha1!$D$20
Name TotalCompradoFIIs: Planilha1!#REF!
Name TotalVendidoFIIs: Planilha1!#REF!

Sheet Planilha1
B11: CONFIGURAÇÕES
B12: Salário | D12: 5000
B13: Rendimento Carteira | D13: 0.01
B14: Sugestão de Investimento | D14: =Salario*40% -> 2000
B17: INVESTIMENTO MENSAL
B18: Quanto investir por mês? | D18: 2000
B19: Quantos Anos? | D19: 5
B20: Rendimento Mensal | D20: 0.01
B21: Imposto de Renda
B22: Patrimonio Bruto Acumulado Final | D22: =FV(TaxaRendMensal,QntdAnos*12,Aporte*(-1)) -> 163339.34
B23: Patrimonio Liquido Acumulado Final
B24: Total de Rendimento Bruto | D24: =FV(TaxaRendMensal,QntdAnos*12,Aporte*(-1)) -> 163339.34
B25: Dividendo Mensal | D25: =PatrimonioAcumulado*RendimentoCarteira -> 1633.3934
B28: CENÁRIOS | D28: DIVIDENDO
B29: Quanto em 2 anos? | C29: =FV(TaxaRendMensal,2*12,Aporte*(-1)) -> 53946.93 | D29: =C29*RendimentoCarteira -> 539.4693
B30: Quanto em 5 anos? | C30: =FV(TaxaRendMensal,5*12,Aporte*(-1)) -> 163339.34 | D30: =C30*$D$13 -> 1633.3934
B31: Quanto em 10 anos? | C31: =FV(TaxaRendMensal,10*12,Aporte*(-1)) -> 460077.38 | D31: =C31*$D$13 -> 4600.7738
B32: Quanto em 20 anos? | C32: =FV(TaxaRendMensal,20*12,Aporte*(-1)) -> 1978510.7 | D32: =C32*$D$13 -> 19785.107
B33: Quanto em 30 anos? | C33: =FV(TaxaRendMensal,30*12,Aporte*(-1)) -> 6989928.3 | D33: =C33*$D$13 -> 69899.283
B36: Perfil | D36: Conservador
B37: Valor a Ser Investido Por Mês | D37: =Aporte -> 2000
B39: Tipo de FII | C39: Percentual Sugerido | D39: Valores
B40: PAPEL | C40: =VLOOKUP($D$36&" - "&B40,Planilha2!$A:$D,4,) -> 0.3 | D40: =C40*$D$37 -> 600
B41: TIJOLO | C41: =VLOOKUP($D$36&" - "&B41,Planilha2!$A:$D,4,) -> 0.5 | D41: =C41*$D$37 -> 1000
B42: HIBRIDOS | C42: =VLOOKUP($D$36&" - "&B42,Planilha2!$A:$D,4,) -> 0.1 | D42: =C42*$D$37 -> 200
B43: FOFs | C43: =VLOOKUP($D$36&" - "&B43,Planilha2!$A:$D,4,) -> 0.1 | D43: =C43*$D$37 -> 200
B44: DESENVOLVIMENTO | C44: =VLOOKUP($D$36&" - "&B44,Planilha2!$A:$D,4,) -> 0 | D44: =C44*$D$37 -> 0
B45: HOTELARIAS | C45: =VLOOKUP($D$36&" - "&B45,Planilha2!$A:$D,4,) -> 0 | D45: =C45*$D$37 -> 0
D46: =SUM(D40:D45) -> 2000

Sheet Planilha2
A2: CHAVE | B2: PERFIL | C2: Tipo de FII | D2: PERCENTUAL
A3: =B3&" - "&C3 -> Conservador - PAPEL | B3: Conservador | C3: PAPEL | D3: 0.3
A4: =B4&" - "&C4 -> Conservador - TIJOLO | B4: Conservador | C4: TIJOLO | D4: 0.5
A5: =B5&" - "&C5 -> Conservador - HIBRIDOS | B5: Conservador | C5: HIBRIDOS | D5: 0.1
A6: =B6&" - "&C6 -> Conservador - FOFs | B6: Conservador | C6: FOFs | D6: 0.1
A7: =B7&" - "&C7 -> Conservador - DESENVOLVIMENTO | B7: Conservador | C7: DESENVOLVIMENTO | D7: 0
A8: =B8&" - "&C8 -> Conservador - HOTELARIAS | B8: Conservador | C8: HOTELARIAS | D8: 0
A9: =B9&" - "&C9 -> Moderado - PAPEL | B9: Moderado | C9: PAPEL | D9: 0.32
A10: =B10&" - "&C10 -> Moderado - TIJOLO | B10: Moderado | C10: TIJOLO | D10: 0.35
A11: =B11&" - "&C11 -> Moderado - HIBRIDOS | B11: Moderado | C11: HIBRIDOS | D11: 0.08
A12: =B12&" - "&C12 -> Moderado - FOFs | B12: Moderado | C12: FOFs | D12: 0.05
A13: =B13&" - "&C13 -> Moderado - DESENVOLVIMENTO | B13: Moderado | C13: DESENVOLVIMENTO | D13: 0.1
A14: =B14&" - "&C14 -> Moderado - HOTELARIAS | B14: Moderado | C14: HOTELARIAS | D14: 0.1
... A20: =B20&" - "&C20 -> Agressivo - HOTELARIAS | B20: Agressivo | C20: HOTELARIAS | D20: 0.1
